odoo/addons/partner_address_split/README.rst
odoo/addons/partner_address_split/__init__.py
odoo/addons/partner_address_split/__manifest__.py
odoo/addons/partner_address_split/i18n/it.po
odoo/addons/partner_address_split/i18n/partner_address_split.pot
odoo/addons/partner_address_split/models/__init__.py
odoo/addons/partner_address_split/models/partner.py
odoo/addons/partner_address_split/readme/CONTRIBUTORS.md
odoo/addons/partner_address_split/readme/DESCRIPTION.md
odoo/addons/partner_address_split/static/description/icon.png
odoo/addons/partner_address_split/static/description/index.html
odoo/addons/partner_address_split/tests/__init__.py
odoo/addons/partner_address_split/tests/test_split_address.py
odoo_addon_partner_address_split-17.0.1.0.0.3.dist-info/METADATA
odoo_addon_partner_address_split-17.0.1.0.0.3.dist-info/WHEEL
odoo_addon_partner_address_split-17.0.1.0.0.3.dist-info/top_level.txt
odoo_addon_partner_address_split-17.0.1.0.0.3.dist-info/RECORD
